advutils/__init__.py
advutils/collections.py
advutils/counters.py
advutils/eventqueue.py
advutils/password.py
advutils/prettylogging.py
advutils/randwords.py
advutils/threader.py
advutils-0.0.2.dist-info/LICENSE.txt
advutils-0.0.2.dist-info/METADATA
advutils-0.0.2.dist-info/WHEEL
advutils-0.0.2.dist-info/top_level.txt
advutils-0.0.2.dist-info/RECORD
